LICENSE
MANIFEST.in
README.md
requirements.txt
setup.py
src/acrolib/__init__.py
src/acrolib/cost_functions.c
src/acrolib/cost_functions.pyx
src/acrolib/dynamic_programming.py
src/acrolib/geometry.py
src/acrolib/plotting.py
src/acrolib/quaternion.py
src/acrolib/sampling.py
src/acrolib.egg-info/PKG-INFO
src/acrolib.egg-info/SOURCES.txt
src/acrolib.egg-info/dependency_links.txt
src/acrolib.egg-info/requires.txt
src/acrolib.egg-info/top_level.txt