Metadata-Version: 2.1
Name: acrolib
Version: 0.0.6
Summary: General utilities for my robotics research at ACRO.
Home-page: https://github.com/JeroenDM/acrolib
Author: Jeroen De Maeyer
Author-email: jeroen.demaeyer@kuleuven.be
License: UNKNOWN
Platform: UNKNOWN
Classifier: Programming Language :: Python :: 3
Classifier: License :: OSI Approved :: MIT License
Classifier: Operating System :: OS Independent
Requires-Python: >=3.6
